.gitattributes
.gitignore
.gitlab-ci.yml
LICENSE
Makefile
dirs.tex
intexrity.tex
make.bat
readme.rst
setup.py
tox.ini
ApeMan.egg-info/PKG-INFO
ApeMan.egg-info/SOURCES.txt
ApeMan.egg-info/dependency_links.txt
ApeMan.egg-info/not-zip-safe
ApeMan.egg-info/requires.txt
ApeMan.egg-info/top_level.txt
_complex_/__main__.py
_complex_/overlay/__init__.py
_complex_/overlay/_decimal_.py
_complex_/overlay/tiers/__init__.py
_complex_/overlay/tiers/module_a.py
_complex_/overlay/tiers/package_a/__init__.py
_complex_/overlay/tiers/package_a/module_b.py
_complex_/tiers/__init__.py
_complex_/tiers/module_a.py
_complex_/tiers/package_a/__init__.py
_complex_/tiers/package_a/module_b.py
_delete_/Makefile
_delete_/make.bat
_delete_/source/conf.py
_delete_/source/index.rst
_examples_/readme.rst
_examples_/module/__init__.py
_examples_/module/__main__.py
_examples_/module/decimal.py
_examples_/package/__init__.py
_examples_/package/__main__.py
_examples_/package/decimal/__init__.py
_simple_/__main__.py
_simple_/_decimal_.py
_simple_/overlay.py
apeman/__33__.py
apeman/__34__.original.py
apeman/__34__.py
apeman/__34__.replacement.py
apeman/__34__.substitution.py
apeman/__35__.py
apeman/__36__.latest.py
apeman/__36__.py
apeman/__36__.repeats.py
apeman/__init__.py
apeman/__meta__.py
apeman/_apeman.py
apeman/descriptors.py
apeman/utilities.py
apeman/__27__/__init__.py
apeman/__27__/apeman.py
apeman/__27__/descriptors.py
apeman/__27__/pingpong.py
apeman/__27__/utils.py
docs/.gitignore
docs/apeman.rst
docs/conf.py
docs/contribution.rst
docs/faq.rst
docs/glossary.rst
docs/import.rst
docs/index.rst
docs/literature.rst
docs/machinery.rst
docs/objective.rst
docs/observations.rst
docs/overlay.rst
docs/tests.rst
docs/.static/.gitattributes
docs/.static/logo.png
docs/.static/figures/.gitattributes
docs/.static/figures/blackbox.png
docs/.static/figures/impoter.encase.png
docs/.static/figures/overlay.png
docs/.static/figures/34/overlay.png
docs/.static/figures/structure/ModSpec.png
docs/.static/figures/structure/encase.png
docs/.static/figures/structure/finder.png
docs/.static/figures/structure/import.png
docs/.static/figures/structure/importer.png
